mzutils/__init__.py
mzutils/aws_funcs.py
mzutils/computing_funcs.py
mzutils/control_models.py
mzutils/ctsv_funcs.py
mzutils/data_structures.py
mzutils/dataframe_funcs.py
mzutils/gym_space_management.py
mzutils/json_funcs.py
mzutils/list_funcs.py
mzutils/os_funcs.py
mzutils/parser.py
mzutils/probabilities_funcs.py
mzutils/serialize_funcs.py
mzutils/string_funcs.py
mzutils/tf_funcs.py
mzutils/torch_funcs.py
mzutils/nlp_tasks/__init__.py
mzutils/nlp_tasks/data_preprocessing.py
mzutils/nlp_tasks/ner_funcs.py
mzutils/nlp_tasks/nlp_metrics.py
mzutils-0.2022.dist-info/LICENSE
mzutils-0.2022.dist-info/METADATA
mzutils-0.2022.dist-info/WHEEL
mzutils-0.2022.dist-info/top_level.txt
mzutils-0.2022.dist-info/RECORD
