Metadata-Version: 2.1
Name: mzutils
Version: 0.2022
Summary: Mohan Zhang's toolkit
Home-page: https://github.com/Mohan-Zhang-u/mzutils
Author: Mohan Zhang
Author-email: mohan.zhang.mz@gmail.com
Classifier: Programming Language :: Python :: 3
Classifier: License :: OSI Approved :: MIT License
Classifier: Operating System :: OS Independent
License-File: LICENSE
Requires-Dist: sphinxcontrib-napoleon
Requires-Dist: myst-parser
Requires-Dist: sphinx (>=4.0.2)
Requires-Dist: sphinx-rtd-theme (>=1.0.0)
Requires-Dist: linkify-it-py
Requires-Dist: numpy
Requires-Dist: torch
Requires-Dist: torchvision
Requires-Dist: nltk
Requires-Dist: pandas
Provides-Extra: all
Requires-Dist: PyYAML ; extra == 'all'
Requires-Dist: tensorflow ; extra == 'all'
Requires-Dist: hanlp ; extra == 'all'
Requires-Dist: pyarrow ; extra == 'all'
Requires-Dist: s3fs ; extra == 'all'
Requires-Dist: hashfile ; extra == 'all'
Provides-Extra: nlp
Requires-Dist: hanlp ; extra == 'nlp'
Requires-Dist: pyarrow ; extra == 'nlp'
Provides-Extra: tf
Requires-Dist: tensorflow ; extra == 'tf'
Provides-Extra: yaml
Requires-Dist: PyYAML ; extra == 'yaml'
Requires-Dist: s3fs ; extra == 'yaml'
Requires-Dist: hashfile ; extra == 'yaml'
